funmark/Benchmark.py
funmark/__init__.py
funmark/main.py
funmark-0.1.1.data/scripts/Benchmark.py
funmark-0.1.1.data/scripts/main.py
funmark-0.1.1.dist-info/LICENSE
funmark-0.1.1.dist-info/METADATA
funmark-0.1.1.dist-info/WHEEL
funmark-0.1.1.dist-info/entry_points.txt
funmark-0.1.1.dist-info/top_level.txt
funmark-0.1.1.dist-info/RECORD
