Metadata-Version: 2.1
Name: funmark
Version: 0.1.1
Summary: A benchmarking tool for fuctions
Home-page: https://github.com/jai-dewani/fun-mark
Author: Jai Kumar Dewani
Author-email: jai.dewani.99@gmail.com
License: UNKNOWN
Platform: UNKNOWN
Classifier: Development Status :: 2 - Pre-Alpha
Classifier: Operating System :: OS Independent
Classifier: Programming Language :: Python :: 3 :: Only
Classifier: Programming Language :: Python :: 3.8
Classifier: Programming Language :: Python :: 3.7
Classifier: Programming Language :: Python :: 3.6
Classifier: Programming Language :: Python :: 3.5
Classifier: Programming Language :: Python :: 3.4
Classifier: Programming Language :: Python :: 3.3
Classifier: Programming Language :: Python :: 3.2
Classifier: Programming Language :: Python :: 3.1
Classifier: Programming Language :: Python :: 3.0
Requires-Dist: numpy
Requires-Dist: matplotlib
